LICENSE
MANIFEST.in
README.rst
setup.cfg
setup.py
versioneer.py
nusa_alphalens/__init__.py
nusa_alphalens/_version.py
nusa_alphalens/nusa.py
nusa_alphalens/performance.py
nusa_alphalens/plotting.py
nusa_alphalens/tears.py
nusa_alphalens/utils.py
nusa_alphalens.egg-info/PKG-INFO
nusa_alphalens.egg-info/SOURCES.txt
nusa_alphalens.egg-info/dependency_links.txt
nusa_alphalens.egg-info/requires.txt
nusa_alphalens.egg-info/top_level.txt
nusa_alphalens/examples/alphalens_tutorial_on_quantopian.ipynb
nusa_alphalens/examples/daily_factor_synthetic_data.ipynb
nusa_alphalens/examples/event_study.ipynb
nusa_alphalens/examples/event_study_synthetic_data.ipynb
nusa_alphalens/examples/ic_tear.png
nusa_alphalens/examples/intraday_factor.ipynb
nusa_alphalens/examples/intraday_factor_synthetic_data.ipynb
nusa_alphalens/examples/predictive_vs_non-predictive_factor.ipynb
nusa_alphalens/examples/pyfolio_integration.ipynb
nusa_alphalens/examples/returns_tear.png
nusa_alphalens/examples/sector_tear.png
nusa_alphalens/examples/table_tear.png
nusa_alphalens/examples/tear_sheet_walk_through.ipynb
nusa_alphalens/tests/__init__.py
nusa_alphalens/tests/test_performance.py
nusa_alphalens/tests/test_tears.py
nusa_alphalens/tests/test_utils.py